dvhastats/__init__.py
dvhastats/_version.py
dvhastats/machine_learning.py
dvhastats/plot.py
dvhastats/stats.py
dvhastats/ui.py
dvhastats/utilities.py
dvha_stats-0.2.4.post1.dist-info/LICENSE
dvha_stats-0.2.4.post1.dist-info/METADATA
dvha_stats-0.2.4.post1.dist-info/WHEEL
dvha_stats-0.2.4.post1.dist-info/top_level.txt
dvha_stats-0.2.4.post1.dist-info/RECORD
