Metadata-Version: 2.1
Name: dvha-stats
Version: 0.2.4.post1
Summary: A library of prediction and statistical process control tools
Home-page: https://github.com/cutright/DVHA-Stats
Author: Dan Cutright
Author-email: dan.cutright@gmail.com
Maintainer: Dan Cutright
Maintainer-email: dan.cutright@gmail.com
License: MIT License
Download-URL: https://github.com/cutright/DVHA-Stats/archive/master.zip
Keywords: stats,statistical process control,control charts
Platform: UNKNOWN
Classifier: License :: OSI Approved :: MIT License
Classifier: Intended Audience :: End Users/Desktop
Classifier: Intended Audience :: Healthcare Industry
Classifier: Intended Audience :: Science/Research
Classifier: Natural Language :: English
Classifier: Development Status :: 4 - Beta
Classifier: Programming Language :: Python
Classifier: Programming Language :: Python :: 3.6
Classifier: Programming Language :: Python :: 3.7
Classifier: Programming Language :: Python :: 3.8
Classifier: Programming Language :: Python :: 3.9
Classifier: Operating System :: OS Independent
Classifier: Topic :: Scientific/Engineering :: Medical Science Apps.
Classifier: Topic :: Scientific/Engineering :: Physics
Requires-Python: >3.5
Requires-Dist: matplotlib
Requires-Dist: numpy
Requires-Dist: scipy
Requires-Dist: scikit-learn
Requires-Dist: regressors
Requires-Dist: PTable
Requires-Dist: python-dateutil
